typhos/__init__.py
typhos/__main__.py
typhos/_version.py
typhos/alarm.py
typhos/app.py
typhos/cache.py
typhos/cli.py
typhos/display.py
typhos/dynamic_font.py
typhos/func.py
typhos/jira.py
typhos/notes.py
typhos/panel.py
typhos/positioner.py
typhos/related_display.py
typhos/status.py
typhos/suite.py
typhos/textedit.py
typhos/tweakable.py
typhos/utils.py
typhos/variety.py
typhos/version.py
typhos/web.py
typhos/widgets.py
typhos/benchmark/__init__.py
typhos/benchmark/cases.py
typhos/benchmark/device.py
typhos/benchmark/ioc.py
typhos/benchmark/profile.py
typhos/benchmark/utils.py
typhos/examples/__init__.py
typhos/examples/device_classes.py
typhos/examples/panel.py
typhos/examples/positioner.py
typhos/plugins/__init__.py
typhos/plugins/core.py
typhos/plugins/happi.py
typhos/tests/__init__.py
typhos/tests/conftest.py
typhos/tests/empty_saved_suite.py
typhos/tests/happi.cfg
typhos/tests/happi.json
typhos/tests/test_alarm.py
typhos/tests/test_benchmark.py
typhos/tests/test_cache.py
typhos/tests/test_cli.py
typhos/tests/test_display.py
typhos/tests/test_dynamic_font.py
typhos/tests/test_func.py
typhos/tests/test_log.py
typhos/tests/test_notes.py
typhos/tests/test_panel.py
typhos/tests/test_plot.py
typhos/tests/test_positioner.py
typhos/tests/test_related_display.py
typhos/tests/test_status.py
typhos/tests/test_suite.py
typhos/tests/test_utils.py
typhos/tests/test_widgets.py
typhos/tests/variety_ioc.py
typhos/tests/plugins/__init__.py
typhos/tests/plugins/test_core.py
typhos/tests/plugins/test_happi.py
typhos/tests/utils/__init__.py
typhos/tests/utils/big_stylesheet.qss
typhos/tests/utils/display.py
typhos/tests/utils/env_device_notes.yaml
typhos/tests/utils/lenna.png
typhos/tests/utils/python.png
typhos/tests/utils/sig.ui
typhos/tests/utils/tiny_stylesheet.qss
typhos/tests/utils/user_device_notes.yaml
typhos/tools/__init__.py
typhos/tools/core.py
typhos/tools/log.py
typhos/tools/plot.py
typhos/ui/loading.gif
typhos/ui/style.qss
typhos/ui/core/detailed_screen.ui
typhos-4.2.1.dist-info/licenses/AUTHORS.rst
typhos-4.2.1.dist-info/licenses/LICENSE.md
typhos-4.2.1.dist-info/METADATA
typhos-4.2.1.dist-info/WHEEL
typhos-4.2.1.dist-info/entry_points.txt
typhos-4.2.1.dist-info/top_level.txt
typhos-4.2.1.dist-info/RECORD
