Metadata-Version: 2.4
Name: typhos
Version: 4.2.1
Summary: Interface generation for ophyd devices
Author: SLAC National Accelerator Laboratory
License: Copyright (c) 2023, The Board of Trustees of the Leland Stanford Junior
Classifier: Development Status :: 5 - Production/Stable
Classifier: Natural Language :: English
Classifier: Programming Language :: Python :: 3
Requires-Python: >=3.9
License-File: LICENSE.md
License-File: AUTHORS.rst
Requires-Dist: coloredlogs
Requires-Dist: entrypoints
Requires-Dist: numpy
Requires-Dist: numpydoc
Requires-Dist: ophyd
Requires-Dist: pcdsutils
Requires-Dist: platformdirs
Requires-Dist: PyQt5
Requires-Dist: pydm>=1.19.1
Requires-Dist: pyqtgraph
Requires-Dist: pyyaml
Requires-Dist: qdarkstyle
Requires-Dist: qtawesome
Requires-Dist: qtpy
Requires-Dist: timechart
Provides-Extra: test
Requires-Dist: caproto; extra == "test"
Requires-Dist: flake8; extra == "test"
Requires-Dist: ipython>=7.16; extra == "test"
Requires-Dist: jinja2; extra == "test"
Requires-Dist: line_profiler; extra == "test"
Requires-Dist: pcdsdevices>=8.4.0; extra == "test"
Requires-Dist: pytest; extra == "test"
Requires-Dist: pytest-benchmark; extra == "test"
Requires-Dist: pytest-cov; extra == "test"
Requires-Dist: pytest-qt; extra == "test"
Requires-Dist: pytest-timeout; extra == "test"
Requires-Dist: simplejson; extra == "test"
Provides-Extra: doc
Requires-Dist: docs-versions-menu; extra == "doc"
Requires-Dist: happi; extra == "doc"
Requires-Dist: sphinx; extra == "doc"
Requires-Dist: sphinx_rtd_theme; extra == "doc"
Requires-Dist: sphinxcontrib-jquery; extra == "doc"
Dynamic: license-file
